odoo/addons/account_payment_term_cutoff_day/README.rst
odoo/addons/account_payment_term_cutoff_day/__init__.py
odoo/addons/account_payment_term_cutoff_day/__manifest__.py
odoo/addons/account_payment_term_cutoff_day/i18n/account_payment_term_cutoff_day.pot
odoo/addons/account_payment_term_cutoff_day/i18n/ja.po
odoo/addons/account_payment_term_cutoff_day/migrations/18.0.1.0.0/post-migrate.py
odoo/addons/account_payment_term_cutoff_day/models/__init__.py
odoo/addons/account_payment_term_cutoff_day/models/account_move.py
odoo/addons/account_payment_term_cutoff_day/models/account_payment_term_line.py
odoo/addons/account_payment_term_cutoff_day/readme/CONFIGURE.md
odoo/addons/account_payment_term_cutoff_day/readme/DESCRIPTION.md
odoo/addons/account_payment_term_cutoff_day/readme/USAGE.md
odoo/addons/account_payment_term_cutoff_day/static/description/icon.png
odoo/addons/account_payment_term_cutoff_day/static/description/index.html
odoo/addons/account_payment_term_cutoff_day/tests/__init__.py
odoo/addons/account_payment_term_cutoff_day/tests/test_account_invoice_date_due.py
odoo/addons/account_payment_term_cutoff_day/views/account_move_views.xml
odoo/addons/account_payment_term_cutoff_day/views/account_payment_term_views.xml
odoo_addon_account_payment_term_cutoff_day-18.0.1.1.0.2.dist-info/METADATA
odoo_addon_account_payment_term_cutoff_day-18.0.1.1.0.2.dist-info/WHEEL
odoo_addon_account_payment_term_cutoff_day-18.0.1.1.0.2.dist-info/top_level.txt
odoo_addon_account_payment_term_cutoff_day-18.0.1.1.0.2.dist-info/RECORD
